<?xml version="1.0" encoding="utf-8"?>
<optionset Name="cr431_eventtype" localizedName="EventType" xmlns:xsi="http://www.w3.org/2001/XMLSchema-instance">
  <OptionSetType>picklist</OptionSetType>
  <IsGlobal>1</IsGlobal>
  <IntroducedVersion>1.0.0.0</IntroducedVersion>
  <IsCustomizable>1</IsCustomizable>
  <ExternalTypeName></ExternalTypeName>
  <displaynames>
    <displayname description="EventType" languagecode="1033" />
  </displaynames>
  <options>
    <option value="254460000" ExternalValue="">
      <labels>
        <label description="Distributor meet" languagecode="1033" />
      </labels>
      <Descriptions>
        <Description description="" languagecode="1033" />
      </Descriptions>
    </option>
    <option value="254460001" ExternalValue="">
      <labels>
        <label description="Retailer meet" languagecode="1033" />
      </labels>
      <Descriptions>
        <Description description="" languagecode="1033" />
      </Descriptions>
    </option>
    <option value="254460002" ExternalValue="">
      <labels>
        <label description="Live demo" languagecode="1033" />
      </labels>
      <Descriptions>
        <Description description="" languagecode="1033" />
      </Descriptions>
    </option>
    <option value="254460003" ExternalValue="">
      <labels>
        <label description="Product stall" languagecode="1033" />
      </labels>
      <Descriptions>
        <Description description="" languagecode="1033" />
      </Descriptions>
    </option>
    <option value="254460004" ExternalValue="">
      <labels>
        <label description="Influencer meet" languagecode="1033" />
      </labels>
      <Descriptions>
        <Description description="" languagecode="1033" />
      </Descriptions>
    </option>
    <option value="254460005" ExternalValue="">
      <labels>
        <label description="Road show" languagecode="1033" />
      </labels>
      <Descriptions>
        <Description description="" languagecode="1033" />
      </Descriptions>
    </option>
  </options>
</optionset>